CHANGELOG
README
amifs_server
amifs_server.bat
license.txt
setup.py
amifs/__init__.py
amifs/config.py
amifs/entry.py
amifs/fs.py
amifs/license.txt
amifs/utils.py
amifs_core.egg-info/PKG-INFO
amifs_core.egg-info/SOURCES.txt
amifs_core.egg-info/dependency_links.txt
amifs_core.egg-info/not-zip-safe
amifs_core.egg-info/requires.txt
amifs_core.egg-info/top_level.txt