Metadata-Version: 1.0
Name: amifs-core
Version: 1.0.0-beta1
Summary: ATLAS Metadata Interface File System (AMIFS)
Home-page: http://ami.in2p3.fr/
Author: Jerome Odier
Author-email: jerome.odier@cern.ch
License: CeCILL-C
Platform: UNKNOWN
